{
  "id": "topdown",
  "display_name": "Top-Down",
  "icon": "🗺️",
  "description": "Top-down adventure / RPG",
  "default_theme": "fantasy",
  "default_geometry": "topdown",
  "themes": ["fantasy", "classic", "nature", "japan", "military"],
  "main_scene": "topdown_main.tscn",
  "scenes": ["pause_subscreen.tscn"],
  "tuning": {
    "move_speed": 200
  },
  "nav_wiring": {
    "main_menu.tscn":         { "GameScene": "res://scenes/main/topdown_main.tscn", "Settings": "res://scenes/ui/settings_menu.tscn" },
    "pause_menu.tscn":        { "Settings": "res://scenes/ui/settings_menu.tscn", "MainMenu": "res://scenes/ui/main_menu.tscn" },
    "game_over.tscn":         { "MainMenu": "res://scenes/ui/main_menu.tscn", "GameScene": "res://scenes/main/topdown_main.tscn" },
    "pause_subscreen.tscn":   { "Settings": "res://scenes/ui/settings_menu.tscn", "MainMenu": "res://scenes/ui/main_menu.tscn" }
  }
}
